bayte/__init__.py
bayte/_meta.py
bayte/encoder.py
bayte/ensemble.py
bayte/plots.py
bayte-0.2.1.dist-info/LICENSE
bayte-0.2.1.dist-info/METADATA
bayte-0.2.1.dist-info/WHEEL
bayte-0.2.1.dist-info/top_level.txt
bayte-0.2.1.dist-info/RECORD
