Metadata-Version: 2.1
Name: bayte
Version: 0.2.1
Summary: Bayesian target encoding with scikit-learn and scipy
Author-email: Akshay Gupta <akgcodes@gmail.com>
License: MIT License
Project-URL: documentation, https://bayte.readthedocs.io/
Project-URL: repository, https://github.com/ak-gupta/bayte
Classifier: Development Status :: 4 - Beta
Classifier: License :: OSI Approved :: MIT License
Classifier: Natural Language :: English
Classifier: Programming Language :: Python :: 3
Classifier: Programming Language :: Python :: 3 :: Only
Classifier: Programming Language :: Python :: 3.8
Classifier: Programming Language :: Python :: 3.9
Classifier: Programming Language :: Python :: 3.10
Classifier: Programming Language :: Python :: 3.11
Requires-Python: >=3.8.0
License-File: LICENSE
Requires-Dist: pandas <=2.2.2,>=1.0.0
Requires-Dist: scikit-learn <=1.4.2,>=1.0.0
Provides-Extra: build
Requires-Dist: build ; extra == 'build'
Requires-Dist: bumpver ; extra == 'build'
Requires-Dist: twine ; extra == 'build'
Requires-Dist: wheel ; extra == 'build'
Provides-Extra: dev
Requires-Dist: bayte[build] ; extra == 'dev'
Requires-Dist: bayte[docs] ; extra == 'dev'
Requires-Dist: bayte[experiments] ; extra == 'dev'
Requires-Dist: bayte[plots] ; extra == 'dev'
Requires-Dist: bayte[qa] ; extra == 'dev'
Requires-Dist: bayte[tests] ; extra == 'dev'
Provides-Extra: docs
Requires-Dist: furo ; extra == 'docs'
Requires-Dist: myst-nb ; extra == 'docs'
Requires-Dist: sphinx ; extra == 'docs'
Requires-Dist: sphinxcontrib-bibtex ; extra == 'docs'
Requires-Dist: sphinx-tabs ; extra == 'docs'
Provides-Extra: experiments
Requires-Dist: category-encoders ==2.3.0 ; extra == 'experiments'
Requires-Dist: lazyscribe ==0.3.0 ; extra == 'experiments'
Requires-Dist: lightgbm ==3.3.1 ; extra == 'experiments'
Requires-Dist: seaborn <=0.13.2,>=0.11.0 ; extra == 'experiments'
Requires-Dist: prefect ==0.15.10 ; extra == 'experiments'
Requires-Dist: xgboost ==1.5.1 ; extra == 'experiments'
Provides-Extra: plots
Requires-Dist: seaborn <=0.13.2,>=0.11.0 ; extra == 'plots'
Provides-Extra: qa
Requires-Dist: ruff ==0.3.7 ; extra == 'qa'
Requires-Dist: mypy ; extra == 'qa'
Requires-Dist: pip-tools ; extra == 'qa'
Provides-Extra: tests
Requires-Dist: pytest ; extra == 'tests'
Requires-Dist: pytest-cov ; extra == 'tests'
